sigconv/__init__.py
sigconv/main.py
sigconv-0.1.0.dist-info/LICENSE
sigconv-0.1.0.dist-info/METADATA
sigconv-0.1.0.dist-info/WHEEL
sigconv-0.1.0.dist-info/entry_points.txt
sigconv-0.1.0.dist-info/top_level.txt
sigconv-0.1.0.dist-info/RECORD
