Metadata-Version: 2.1
Name: sigconv
Version: 0.1.0
Summary: Convert binary signature patterns between spaced format, escaped format, and bytes+mask format used in reverse engineering and pattern scanning.
Home-page: https://github.com/zwalloc/sigconv
Author: AleirJDawn
Author-email: 
Classifier: Programming Language :: Python :: 3
Classifier: License :: OSI Approved :: MIT License
Requires-Python: >=3.6
License-File: LICENSE
